Workbook

Sheet  COOKIES 
A1: Order ID | B1: Customer ID | C1: Customer name | D1: Cookies Shipped | E1: Revenue | F1: Cost | G1: profit | H1: Order Date | I1: Ship Date | J1: days to ship
A2: 474264 | B2: 152689 | C2: YT Restaurants | D2: 466 | E2: 2330 | F2: 1165 | G2: =Order_Data[[#This Row],[Revenue]]-Order_Data[[#This Row],[Cost]] -> 1165 | H2: 43464 | I2: 43470 | J2: 6
A3: 478235 | B3: 152689 | C3: YT Restaurants | D3: 524 | E3: 2620 | F3: 1310 | G3: 1310 | H3: 43463 | I3: 43468 | J3: 5
A4: 641929 | B4: 452584 | C4: Acme Grocery Stores | D4: 710 | E4: 3550 | F4: 1775 | G4: 1775 | H4: 43465 | I4: 43467 | J4: 2
A5: 684340 | B5: 985245 | C5: Quick Bite Convenience Stores | D5: 868 | E5: 4340 | F5: 2170 | G5: 2170 | H5: 43464 | I5: 43467 | J5: 3
A6: 278043 | B6: 785432 | C6: Park & Eat LLC | D6: 497 | E6: 2485 | F6: 1242.5 | G6: 1242.5 | H6: 43463 | I6: 43467 | J6: 4
A7: 786770 | B7: 985245 | C7: Quick Bite Convenience Stores | D7: 343 | E7: 1715 | F7: 857.5 | G7: 857.5 | H7: 43462 | I7: 43466 | J7: 4
A8: 589574 | B8: 985245 | C8: Quick Bite Convenience Stores | D8: 369 | E8: 1845 | F8: 922.5 | G8: 922.5 | H8: 43462 | I8: 43466 | J8: 4
A9: 487021 | B9: 785432 | C9: Park & Eat LLC | D9: 895 | E9: 4475 | F9: 2237.5 | G9: 2237.5 | H9: 43462 | I9: 43466 | J9: 4
A10: 397607 | B10: 985245 | C10: Quick Bite Convenience Stores | D10: 642 | E10: 3210 | F10: 1605 | G10: 1605 | H10: 43462 | I10: 43465 | J10: 3
A11: 219369 | B11: 985245 | C11: Quick Bite Convenience Stores | D11: 83 | E11: 415 | F11: 207.5 | G11: 207.5 | H11: 43461 | I11: 43465 | J11: 4
A12: 602410 | B12: 325698 | C12: Cascade Grovers | D12: 65 | E12: 325 | F12: 162.5 | G12: 162.5 | H12: 43462 | I12: 43464 | J12: 2
A13: 422605 | B13: 325698 | C13: Cascade Grovers | D13: 874 | E13: 4370 | F13: 2185 | G13: 2185 | H13: 43461 | I13: 43464 | J13: 3
A14: 715284 | B14: 152689 | C14: YT Restaurants | D14: 889 | E14: 4445 | F14: 2222.5 | G14: 2222.5 | H14: 43459 | I14: 43464 | J14: 5
... A846: 140095 | B846: 452584 | C846: Acme Grocery Stores | D846: 661 | E846: 3305 | F846: 1652.5 | G846: 1652.5 | H846: 43101 | I846: 43103 | J846: 2

Sheet Executive Dashboard
B2: EXECUTIVE DASHBOARD - Cookie Sales Performance
B4: KEY PERFORMANCE INDICATORS
B5: Total Revenue | C5: Total Profit | D5: Margin | F5: Cookies Shipped | G5: Total Orders
B6: =SUM(' COOKIES '!E:E) -> 2233025 | C6: =SUM(' COOKIES '!G:G) -> 1116512.5 | D6: =C6/B6 -> 0.5 | F6: =SUM(' COOKIES '!D:D) -> 446605 | G6: =COUNTA(' COOKIES '!A:A)-1 -> 845
B8: REVENUE BY CUSTOMER | F8: PROFIT BY CUSTOMER
B9: Customer | C9: Revenue | D9: % Share | F9: Customer | G9: Profit | H9: Margin
B10: {=_xlfn._xlws.SORT(_xlfn.UNIQUE(' COOKIES '!C2:C846),1,1)} -> Acme Grocery Stores | C10: =SUMIF(' COOKIES '!C:C,B10,' COOKIES '!E:E) -> 157505 | D10: =C10/SUM(C10:C14) -> 0.070534365 | F10: =B10 -> Acme Grocery Stores | G10: =SUMIF(' COOKIES '!C:C,F10,' COOKIES '!G:G) -> 78752.5 | H10: =G10/C10 -> 0.5
B11: Cascade Grovers | C11: =SUMIF(' COOKIES '!C:C,B11,' COOKIES '!E:E) -> 649740 | D11: =C11/SUM(C10:C14) -> 0.29096853 | F11: =B11 -> Cascade Grovers | G11: =SUMIF(' COOKIES '!C:C,F11,' COOKIES '!G:G) -> 324870 | H11: =G11/C11 -> 0.5
B12: Park & Eat LLC | C12: =SUMIF(' COOKIES '!C:C,B12,' COOKIES '!E:E) -> 395290 | D12: =C12/SUM(C10:C14) -> 0.17701996 | F12: =B12 -> Park & Eat LLC | G12: =SUMIF(' COOKIES '!C:C,F12,' COOKIES '!G:G) -> 197645 | H12: =G12/C12 -> 0.5
B13: Quick Bite Convenience Stores | C13: =SUMIF(' COOKIES '!C:C,B13,' COOKIES '!E:E) -> 557170 | D13: =C13/SUM(C10:C14) -> 0.24951355 | F13: =B13 -> Quick Bite Convenience Stores | G13: =SUMIF(' COOKIES '!C:C,F13,' COOKIES '!G:G) -> 278585 | H13: =G13/C13 -> 0.5
B14: YT Restaurants | C14: =SUMIF(' COOKIES '!C:C,B14,' COOKIES '!E:E) -> 473320 | D14: =C14/SUM(C10:C14) -> 0.21196359 | F14: =B14 -> YT Restaurants | G14: =SUMIF(' COOKIES '!C:C,F14,' COOKIES '!G:G) -> 236660 | H14: =G14/C14 -> 0.5
B15: TOTAL | C15: =SUM(C10:C14) -> 2233025 | D15: =SUM(D10:D14) -> 1 | F15: TOTAL | G15: =SUM(G10:G14) -> 1116512.5 | H15: =G15/C15 -> 0.5
B17: VISUAL ANALYTICS
B25: KEY INSIGHTS
B26: 🏆 Top Revenue: | C26: Cascade Grovers | D26: 649740 | F26: 📦 Avg Days to Ship: | G26: 3.616568
B27: 💰 Most Profitable: | C27: Cascade Grovers | D27: 324870 | F27: 📊 Avg Order Value: | G27: 2642.6331
B29: Data Source: ' COOKIES ' sheet | Dashboard auto-updates when source data changes
